gqlmod_cirrusci/__init__.py
gqlmod_cirrusci-0.2.dist-info/LICENSE
gqlmod_cirrusci-0.2.dist-info/METADATA
gqlmod_cirrusci-0.2.dist-info/WHEEL
gqlmod_cirrusci-0.2.dist-info/entry_points.txt
gqlmod_cirrusci-0.2.dist-info/top_level.txt
gqlmod_cirrusci-0.2.dist-info/RECORD
